fishrotate/RoateAnimation.py
fishrotate/__init__.py
fishrotate/fishrotate.py
fishrotate-0.1.0.data/data/share/ament_index/resource_index/packages/fishrotate
fishrotate-0.1.0.data/data/share/fishrotate/package.xml
fishrotate-0.1.0.dist-info/METADATA
fishrotate-0.1.0.dist-info/WHEEL
fishrotate-0.1.0.dist-info/entry_points.txt
fishrotate-0.1.0.dist-info/top_level.txt
fishrotate-0.1.0.dist-info/zip-safe
fishrotate-0.1.0.dist-info/RECORD
